sqlitedict.py
restricted_sqlitedict-1.0.0.dist-info/LICENSE.md
restricted_sqlitedict-1.0.0.dist-info/METADATA
restricted_sqlitedict-1.0.0.dist-info/WHEEL
restricted_sqlitedict-1.0.0.dist-info/top_level.txt
restricted_sqlitedict-1.0.0.dist-info/RECORD
