Metadata-Version: 2.1
Name: restricted-sqlitedict
Version: 1.0.0
Summary: Fork of sqlitedict with restricted pickle loading.
Home-page: https://github.com/mstopa/restricted-sqlitedict
Download-URL: http://pypi.python.org/pypi/restricted-sqlitedict
Author: Radim Rehurek, Victor R. Escobar, Andrey Usov, Prasanna Swaminathan, Jeff Quast, Maciek Stopa
Author-email: me@radimrehurek.com
Maintainer: Radim Rehurek
Maintainer-email: me@radimrehurek.com
License: Apache 2.0
Keywords: sqlite,persistent dict,multithreaded
Platform: any
Classifier: Development Status :: 5 - Production/Stable
Classifier: Environment :: Console
Classifier: Intended Audience :: Developers
Classifier: License :: OSI Approved :: Apache Software License
Classifier: Operating System :: OS Independent
Classifier: Programming Language :: Python :: 3.7
Classifier: Programming Language :: Python :: 3.8
Classifier: Programming Language :: Python :: 3.9
Classifier: Programming Language :: Python :: 3.10
Classifier: Topic :: Database :: Front-Ends
License-File: LICENSE.md
